graphrag_for_all/__init__.py
graphrag_for_all/run_index.py
graphrag_for_all/secret.py
graphrag_for_all/df_ops/__init__.py
graphrag_for_all/df_ops/aggregate.py
graphrag_for_all/df_ops/chunk.py
graphrag_for_all/df_ops/cluster_graph.py
graphrag_for_all/df_ops/compute_edge_combined_degree.py
graphrag_for_all/df_ops/concat.py
graphrag_for_all/df_ops/convert.py
graphrag_for_all/df_ops/copy.py
graphrag_for_all/df_ops/create_community_reports.py
graphrag_for_all/df_ops/dedupe.py
graphrag_for_all/df_ops/defaults.py
graphrag_for_all/df_ops/drop.py
graphrag_for_all/df_ops/entity_extract.py
graphrag_for_all/df_ops/fill.py
graphrag_for_all/df_ops/filter.py
graphrag_for_all/df_ops/genid.py
graphrag_for_all/df_ops/join.py
graphrag_for_all/df_ops/layout_graph.py
graphrag_for_all/df_ops/merge.py
graphrag_for_all/df_ops/merge_graphs.py
graphrag_for_all/df_ops/orderby.py
graphrag_for_all/df_ops/prepare_community_reports.py
graphrag_for_all/df_ops/rename.py
graphrag_for_all/df_ops/restore_community_hierarchy.py
graphrag_for_all/df_ops/schemas.py
graphrag_for_all/df_ops/select.py
graphrag_for_all/df_ops/summarize_descriptions.py
graphrag_for_all/df_ops/text_embed.py
graphrag_for_all/df_ops/text_split.py
graphrag_for_all/df_ops/unpack.py
graphrag_for_all/df_ops/unroll.py
graphrag_for_all/df_ops/unzip.py
graphrag_for_all/df_ops/window.py
graphrag_for_all/df_ops/zip.py
graphrag_for_all/generators/__init__.py
graphrag_for_all/generators/community_reports_extractor.py
graphrag_for_all/generators/graph_extactor.py
graphrag_for_all/generators/summarize_extractor.py
graphrag_for_all/index/__init__.py
graphrag_for_all/index/generate.py
graphrag_for_all/index/graphrag.py
graphrag_for_all/index/vectorstore.py
graphrag_for_all/lc_helper/__init__.py
graphrag_for_all/lc_helper/wrapper.py
graphrag_for_all/llm/__init__.py
graphrag_for_all/llm/create.py
graphrag_for_all/llm/huggingface.py
graphrag_for_all/llm/openai.py
graphrag_for_all/llm/send.py
graphrag_for_all/llm/system.py
graphrag_for_all-0.1.12.dist-info/METADATA
graphrag_for_all-0.1.12.dist-info/WHEEL
graphrag_for_all-0.1.12.dist-info/top_level.txt
graphrag_for_all-0.1.12.dist-info/RECORD
